[{"id":1,"titulo":"Site Constructor","imagem":"img1.jpg","autor":"Thiago Souza","foto":"author1.jpg","ano":2023},{"id":2,"titulo":"O Conde de Monte Cristo","imagem":"img30.jpg","autor":"Alexandre Dumas","foto":"author30.jpg","ano":1844},{"id":3,"titulo":"Harry Potter e a Pedra Filosofal","imagem":"img3.jpg","autor":"J.K. Rowling","foto":"author3.jpg","ano":1997},{"id":4,"titulo":"A Menina que Roubava Livros","imagem":"img4.jpg","autor":"Markus Zusak","foto":"author4.jpg","ano":2005},{"id":5,"titulo":"dom Quixote","imagem":"img5.jpg","autor":"Miguel de Cervantes","foto":"author5.jpg","ano":1605},{"id":6,"titulo":"A Guerra dos Tronos","imagem":"img6.jpg","autor":"George R.R. Martin","foto":"author6.jpg","ano":1996},{"id":7,"titulo":"O Pequeno Príncipe","imagem":"img7.jpg","autor":"Antoine de Saint-Exupéry","foto":"author7.jpg","ano":1943},{"id":8,"titulo":"Orgulho e Preconceito","imagem":"img8.jpg","autor":"Jane Austen","foto":"author8.jpg","ano":1813},{"id":9,"titulo":"1984","imagem":"img9.jpg","autor":"George Orwell","foto":"author9.jpg","ano":1949},{"id":10,"titulo":"A Revolução dos Bichos","imagem":"img10.jpg","autor":"George Orwell","foto":"author10.jpg","ano":1945},{"id":11,"titulo":"A Culpa é das Estrelas","imagem":"img11.jpg","autor":"John Green","foto":"author11.jpg","ano":2012},{"id":12,"titulo":"A Metamorfose","imagem":"img12.jpg","autor":"Franz Kafka","foto":"author12.jpg","ano":1915},{"id":13,"titulo":"O Sol é para Todos","imagem":"img13.jpg","autor":"Harper Lee","foto":"author13.jpg","ano":1960},{"id":14,"titulo":"Crime e Castigo","imagem":"img14.jpg","autor":"Fiódor dostoiévski","foto":"author14.jpg","ano":1866},{"id":15,"titulo":"A Revolta de Atlas","imagem":"img15.jpg","autor":"Ayn Rand","foto":"author15.jpg","ano":1957},{"id":16,"titulo":"O Hobbit","imagem":"img16.jpg","autor":"J.R.R. Tolkien","foto":"author16.jpg","ano":1937},{"id":17,"titulo":"Cem Anos de Solidão","imagem":"img17.jpg","autor":"Gabriel García Márquez","foto":"author17.jpg","ano":1967},{"id":18,"titulo":"As Crônicas de Nárnia","imagem":"img18.jpg","autor":"C.S. Lewis","foto":"author18.jpg","ano":1950},{"id":19,"titulo":"O Silmarillion","imagem":"img23.jpg","autor":"J.R.R. Tolkien","foto":"author23.jpg","ano":1977}]